README.rst
setup.py
payeer_api/__init__.py
payeer_api/api.py
payeer_api.egg-info/PKG-INFO
payeer_api.egg-info/SOURCES.txt
payeer_api.egg-info/dependency_links.txt
payeer_api.egg-info/top_level.txt