Metadata-Version: 1.1
Name: payeer-api
Version: 0.1
Summary: Python Payeer API client
Home-page: https://github.com/AshotS/payeer_api
Author: AshotS
Author-email: sarckisyanashot@yandex.ru
License: MIT license
Keywords: payeer
Platform: UNKNOWN
Requires: requests
